btch_downloader/__init__.py
btch_downloader/downloader.py
btch_downloader-4.0.18.dist-info/licenses/LICENSE
btch_downloader-4.0.18.dist-info/METADATA
btch_downloader-4.0.18.dist-info/WHEEL
btch_downloader-4.0.18.dist-info/top_level.txt
btch_downloader-4.0.18.dist-info/RECORD
