Metadata-Version: 2.4
Name: btch-downloader
Version: 4.0.18
Summary: Social Media Downloader for Python
Author-email: Tio <tioclkp02@gmail.com>
License: MIT License
Project-URL: Homepage, https://github.com/hostinger-bot/btch-downloader-py
Project-URL: Repository, https://github.com/hostinger-bot/btch-downloader-py.git
Project-URL: Issues, https://github.com/hostinger-bot/btch-downloader-py/issues
Keywords: AIO,Instagram,TikTok,Facebook,YouTube,Twitter,MediaFire,Capcut,Gdrive,Pinterest
Classifier: Programming Language :: Python :: 3
Classifier: License :: OSI Approved :: MIT License
Classifier: Operating System :: OS Independent
Requires-Python: >=3.8
License-File: LICENSE
Requires-Dist: httpx>=0.24.0
Dynamic: license-file
